{
    "apple": [
        {
            "feature": "LIWC_Negate",
            "correlation": 0.3237388599164063
        },
        {
            "feature": "LIWC_Excl",
            "correlation": 0.30088798311126275
        },
        {
            "feature": "LIWC_Family",
            "correlation": -0.25471182256977565
        },
        {
            "feature": "LIWC_Dissent",
            "correlation": 0.22495826152353038
        },
        {
            "feature": "LIWC_I",
            "correlation": -0.20987964968866035
        },
        {
            "feature": "vader_neg",
            "correlation": 0.20586694240570091
        },
        {
            "feature": "LIWC_Numbers",
            "correlation": -0.205431080594007
        },
        {
            "feature": "LIWC_Ppron",
            "correlation": -0.1980299700448828
        },
        {
            "feature": "LIWC_Space",
            "correlation": -0.18088384154225898
        },
        {
            "feature": "LIWC_Discrep",
            "correlation": 0.17926332265499317
        },
        {
            "feature": "LIWC_Motion",
            "correlation": -0.17837829889893747
        },
        {
            "feature": "LIWC_Sexual",
            "correlation": 0.17654730334378693
        },
        {
            "feature": "LIWC_Humans",
            "correlation": 0.1756001404675372
        },
        {
            "feature": "LIWC_Cause",
            "correlation": 0.16977325950804545
        },
        {
            "feature": "LIWC_Insight",
            "correlation": 0.1673755405157276
        },
        {
            "feature": "LIWC_Article",
            "correlation": 0.1653874762130871
        },
        {
            "feature": "frac_special",
            "correlation": 0.16382002384331784
        },
        {
            "feature": "frac_digits",
            "correlation": -0.16323707712526675
        },
        {
            "feature": "LIWC_Relativ",
            "correlation": -0.16188857670614104
        },
        {
            "feature": "frac_stopwords",
            "correlation": -0.15372749146644732
        }
    ],
    "tesla": [
        {
            "feature": "LIWC_You",
            "correlation": 0.28967226463598506
        },
        {
            "feature": "vader_neg",
            "correlation": -0.2704938544814424
        },
        {
            "feature": "LIWC_Filler",
            "correlation": -0.25583606694041594
        },
        {
            "feature": "LIWC_Sad",
            "correlation": -0.2333131028822024
        },
        {
            "feature": "LIWC_Social",
            "correlation": 0.23282654185159404
        },
        {
            "feature": "vader_compound",
            "correlation": -0.22870452797272986
        },
        {
            "feature": "LIWC_Verbs",
            "correlation": 0.20724839566507955
        },
        {
            "feature": "LIWC_Discrep",
            "correlation": 0.20012855131857366
        },
        {
            "feature": "LIWC_AuxVb",
            "correlation": 0.19673142895701778
        },
        {
            "feature": "LIWC_Friends",
            "correlation": 0.19338983211079105
        },
        {
            "feature": "LIWC_Pronoun",
            "correlation": 0.18749522753230224
        },
        {
            "feature": "LIWC_Certain",
            "correlation": -0.18235558400608332
        },
        {
            "feature": "LIWC_Excl",
            "correlation": 0.16817937110316789
        },
        {
            "feature": "LIWC_Space",
            "correlation": 0.16629074638389313
        },
        {
            "feature": "frac_digits",
            "correlation": -0.166031819085879
        },
        {
            "feature": "LIWC_Incl",
            "correlation": 0.15683010792374272
        },
        {
            "feature": "LIWC_Ipron",
            "correlation": 0.1564418008006116
        },
        {
            "feature": "LIWC_Relativ",
            "correlation": 0.14992106096723948
        },
        {
            "feature": "LIWC_Motion",
            "correlation": -0.14487691488491428
        },
        {
            "feature": "LIWC_Negemo",
            "correlation": -0.14105869965836096
        }
    ],
    "nvidia": [
        {
            "feature": "LIWC_Home",
            "correlation": 0.27322963027204933
        },
        {
            "feature": "LIWC_Friends",
            "correlation": -0.25202310321391025
        },
        {
            "feature": "LIWC_Hear",
            "correlation": 0.24819087704217418
        },
        {
            "feature": "LIWC_Motion",
            "correlation": 0.2445977618400042
        },
        {
            "feature": "LIWC_Work",
            "correlation": -0.2418522218706109
        },
        {
            "feature": "LIWC_Dissent",
            "correlation": 0.2384353973011779
        },
        {
            "feature": "LIWC_Social",
            "correlation": -0.23660187874993083
        },
        {
            "feature": "LIWC_Article",
            "correlation": 0.2016163492953481
        },
        {
            "feature": "LIWC_Time",
            "correlation": -0.19816188234219295
        },
        {
            "feature": "vader_neg",
            "correlation": 0.1981228774897043
        },
        {
            "feature": "LIWC_Funct",
            "correlation": -0.1930208496740317
        },
        {
            "feature": "LIWC_Cause",
            "correlation": 0.19056810097745225
        },
        {
            "feature": "LIWC_Percept",
            "correlation": 0.18902882562657244
        },
        {
            "feature": "LIWC_Swear",
            "correlation": 0.1769481463817315
        },
        {
            "feature": "LIWC_Nonflu",
            "correlation": -0.1721339425657787
        },
        {
            "feature": "LIWC_Leisure",
            "correlation": -0.17102302114432777
        },
        {
            "feature": "LIWC_Conj",
            "correlation": 0.17032412136853536
        },
        {
            "feature": "frac_special",
            "correlation": -0.1660350937555133
        },
        {
            "feature": "LIWC_Negate",
            "correlation": 0.1606192795855372
        },
        {
            "feature": "LIWC_Health",
            "correlation": -0.15901051324887086
        }
    ],
    "amazon": [
        {
            "feature": "LIWC_Relativ",
            "correlation": -0.4172999102739252
        },
        {
            "feature": "LIWC_Ipron",
            "correlation": -0.3660983531943141
        },
        {
            "feature": "LIWC_Percept",
            "correlation": -0.32190780066991853
        },
        {
            "feature": "LIWC_See",
            "correlation": -0.30175523168366375
        },
        {
            "feature": "num_long_sentences",
            "correlation": -0.2992885798815716
        },
        {
            "feature": "num_unique_stopwords",
            "correlation": -0.2958277974828587
        },
        {
            "feature": "num_sentences",
            "correlation": -0.2865233957596989
        },
        {
            "feature": "LIWC_They",
            "correlation": 0.28445281626377283
        },
        {
            "feature": "num_words",
            "correlation": -0.2775460040467589
        },
        {
            "feature": "LIWC_Time",
            "correlation": -0.2744134012821469
        },
        {
            "feature": "num_chars",
            "correlation": -0.2718704943585026
        },
        {
            "feature": "frac_digits",
            "correlation": -0.2700675386742951
        },
        {
            "feature": "frac_alpha",
            "correlation": -0.26367006717549546
        },
        {
            "feature": "avg_word_len",
            "correlation": 0.2627968801433117
        },
        {
            "feature": "LIWC_Ppron",
            "correlation": 0.25376915328187577
        },
        {
            "feature": "LIWC_Assent",
            "correlation": -0.2521390902309336
        },
        {
            "feature": "num_chars_no_whitespace",
            "correlation": -0.24918041288227408
        },
        {
            "feature": "LIWC_Feel",
            "correlation": -0.2463771222605005
        },
        {
            "feature": "LIWC_Work",
            "correlation": 0.2425102931717881
        },
        {
            "feature": "LIWC_Space",
            "correlation": -0.23220085532055595
        }
    ],
    "google": [
        {
            "feature": "LIWC_Anx",
            "correlation": 0.40420407843960127
        },
        {
            "feature": "num_words",
            "correlation": 0.37466828759883103
        },
        {
            "feature": "num_chars_no_whitespace",
            "correlation": 0.36971495445478975
        },
        {
            "feature": "num_chars",
            "correlation": 0.34930850522669976
        },
        {
            "feature": "num_unique_words",
            "correlation": 0.32656062574394984
        },
        {
            "feature": "num_long_words",
            "correlation": 0.3123938129028797
        },
        {
            "feature": "LIWC_Filler",
            "correlation": 0.29707405578625434
        },
        {
            "feature": "LIWC_Time",
            "correlation": -0.2666082239718142
        },
        {
            "feature": "LIWC_Relativ",
            "correlation": -0.2545097597288152
        },
        {
            "feature": "LIWC_CogMech",
            "correlation": -0.25358533704810526
        },
        {
            "feature": "LIWC_Relig",
            "correlation": 0.24996777138413107
        },
        {
            "feature": "LIWC_SheHe",
            "correlation": 0.24521867124021732
        },
        {
            "feature": "LIWC_Humans",
            "correlation": 0.22754693972494724
        },
        {
            "feature": "frac_special",
            "correlation": 0.21962993953362653
        },
        {
            "feature": "LIWC_Negemo",
            "correlation": 0.21299095559307596
        },
        {
            "feature": "LIWC_Social",
            "correlation": 0.2127009633085295
        },
        {
            "feature": "automated_readability_index",
            "correlation": 0.202095173974372
        },
        {
            "feature": "LIWC_Affect",
            "correlation": 0.20184763967603317
        },
        {
            "feature": "num_long_sentences",
            "correlation": 0.20161122247724872
        },
        {
            "feature": "avg_words_per_sentence",
            "correlation": 0.19757979706963769
        }
    ]
}